cognito_oauthtools/__init__.py
cognito_oauthtools-1.0.1.dist-info/LICENSE
cognito_oauthtools-1.0.1.dist-info/METADATA
cognito_oauthtools-1.0.1.dist-info/WHEEL
cognito_oauthtools-1.0.1.dist-info/top_level.txt
cognito_oauthtools-1.0.1.dist-info/RECORD
