Metadata-Version: 2.1
Name: cognito-oauthtools
Version: 1.0.1
Summary: Simple AWS Cognito client to simplify implementation
Home-page: https://github.com/josephbmanley/cognito-oauthtools
Author: Joseph Manley
Author-email: j@cloudsumu.com
License: GPL3.0
Keywords: AWS,Cognito,OAuth
Platform: UNKNOWN
Classifier: Development Status :: 5 - Production/Stable
Classifier: Intended Audience :: Developers
Classifier: License :: OSI Approved :: GNU General Public License v3 or later (GPLv3+)
Classifier: Programming Language :: Python :: 2
Classifier: Programming Language :: Python :: 2.7
Classifier: Programming Language :: Python :: 3
Classifier: Programming Language :: Python :: 3.3
Classifier: Programming Language :: Python :: 3.4
Classifier: Programming Language :: Python :: 3.5
Classifier: Programming Language :: Python :: 3.6
Classifier: Programming Language :: Python :: 3.7
Classifier: Programming Language :: Python :: 3.8
Requires-Dist: requests
